isqmap/__init__.py
isqmap/ag.py
isqmap/cir_dg.py
isqmap/cir_dg_swap_depth_opt.py
isqmap/front_circuit.py
isqmap/genetic_swap_depth_opt.py
isqmap/mapping.py
isqmap/monte_carlo_tree.py
isqmap/init_mapping/__init__.py
isqmap/init_mapping/get_init_map.py
isqmap/init_mapping/sa_mapping.py
isqmap/init_mapping/subgraph_isomorphism_mapping.py
isqmap/init_mapping/FiDLS/FiDLS_inimap.py
isqmap/init_mapping/FiDLS/FiDLS_run.py
isqmap/init_mapping/FiDLS/__init__.py
isqmap/init_mapping/FiDLS/ag.py
isqmap/init_mapping/FiDLS/fidls_d.py
isqmap/init_mapping/FiDLS/fidls_g.py
isqmap/init_mapping/FiDLS/inimap.py
isqmap/init_mapping/FiDLS/maps.py
isqmap/init_mapping/FiDLS/readme.txt
isqmap/init_mapping/FiDLS/sqatest0.py
isqmap/init_mapping/FiDLS/utils.py
isqmap/init_mapping/FiDLS/vfs.py
isqmap/init_mapping/FiDLS/vfstest.py
isqmap-0.4.dist-info/LICENSE
isqmap-0.4.dist-info/METADATA
isqmap-0.4.dist-info/WHEEL
isqmap-0.4.dist-info/top_level.txt
isqmap-0.4.dist-info/RECORD
