Metadata-Version: 2.1
Name: isqmap
Version: 0.4
Summary: a qubit mapping package
Author: arclightquantum
Author-email: louhz@arclightquantum.com
Platform: python 3.7+
License-File: LICENSE
Requires-Dist: numpy
Requires-Dist: networkx
Requires-Dist: matplotlib
Requires-Dist: qiskit
